Workbook
Name Slicer_Category: #N/A
Name Slicer_Region: #N/A
Name Slicer_Segment: #N/A

Sheet Sheet1
A3: Row Labels | B3: Sum of Sales | C3: Sum of Profit
A4: Central | B4: 154825.38 | C4: 49271.05
A5: East | B5: 129942.57 | C5: 41922.27
A6: South | B6: 141611.65 | C6: 47214.92
A7: West | B7: 145519.7 | C7: 49329.12
A8: Grand Total | B8: 571899.3 | C8: 187737.36

Sheet Sheet2
A3: Row Labels | B3: Sum of Sales | C3: Sum of Profit | D3: Sum of Discount
A4: Technology | B4: 60714.12 | C4: 18908.71 | D4: 1.2
A5: Accessories | B5: 809.13 | C5: 250.43 | D5: 0.5
A6: Computers | B6: 43265.06 | C6: 13349.16 | D6: 0
A7: Copiers | B7: 5368.4 | C7: 1989.3 | D7: 0.3
A8: Phones | B8: 11271.53 | C8: 3319.82 | D8: 0.4
A9: Grand Total | B9: 60714.12 | C9: 18908.71 | D9: 1.2

Sheet Sales_Data
A1: Order_ID | B1: Order_Date | C1: Ship_Date | D1: Customer_ID | E1: Customer_Name | F1: Segment | G1: Region | H1: State | I1: Category | J1: Sub_Category | K1: Product_Name | L1: Sales | M1: Quantity | N1: Discount | O1: Profit | P1: Profit_Margin%
A2: ORD-10001 | B2: 45216 | C2: 45217 | D2: C-1520 | E2: Alice Johnson | F2: Consumer | G2: West | H2: Oregon | I2: Technology | J2: Accessories | K2: Keyboard | L2: 80.82 | M2: 2 | N2: 0 | O2: 24.44 | P2: =O2/L2 -> 0.3024004
A3: ORD-10002 | B3: 44785 | C3: 44787 | D3: C-3615 | E3: Grace Garcia | F3: Home Office | G3: West | H3: Washington | I3: Office Supplies | J3: Appliances | K3: Coffee Maker | L3: 847.52 | M3: 8 | N3: 0 | O3: 220.61 | P3: =O3/L3 -> 0.26030064
A4: ORD-10003 | B4: 44846 | C4: 44848 | D4: C-8527 | E4: Iris Johnson | F4: Consumer | G4: East | H4: Virginia | I4: Technology | J4: Copiers | K4: Canon Copier | L4: 2127.82 | M4: 6 | N4: 0.1 | O4: 528.16 | P4: =O4/L4 -> 0.24821648
A5: ORD-10004 | B5: 44949 | C5: 44950 | D5: C-2654 | E5: Grace Jones | F5: Home Office | G5: Central | H5: Ohio | I5: Technology | J5: Phones | K5: iPhone 13 | L5: 2156.2 | M5: 4 | N5: 0 | O5: 509.23 | P5: =O5/L5 -> 0.23617011
A6: ORD-10005 | B6: 45026 | C6: 45032 | D6: C-3803 | E6: Iris Brown | F6: Corporate | G6: Central | H6: Illinois | I6: Furniture | J6: Tables | K6: Side Table | L6: 1457.25 | M6: 5 | N6: 0 | O6: 433.85 | P6: =O6/L6 -> 0.29771831
A7: ORD-10006 | B7: 44729 | C7: 44733 | D7: C-1525 | E7: Frank Martinez | F7: Home Office | G7: South | H7: Tennessee | I7: Office Supplies | J7: Paper | K7: Copy Paper | L7: 132.78 | M7: 6 | N7: 0 | O7: 52.15 | P7: =O7/L7 -> 0.39275493
A8: ORD-10007 | B8: 44836 | C8: 44837 | D8: C-9830 | E8: Eve Martinez | F8: Consumer | G8: East | H8: Virginia | I8: Office Supplies | J8: Appliances | K8: Microwave | L8: 694.88 | M8: 8 | N8: 0 | O8: 269.85 | P8: =O8/L8 -> 0.38834043
A9: ORD-10008 | B9: 45159 | C9: 45163 | D9: C-7916 | E9: Jack Johnson | F9: Consumer | G9: Central | H9: Illinois | I9: Office Supplies | J9: Appliances | K9: Coffee Maker | L9: 117.56 | M9: 1 | N9: 0 | O9: 34.46 | P9: =O9/L9 -> 0.29312691
A10: ORD-10009 | B10: 44956 | C10: 44960 | D10: C-8123 | E10: Carol Davis | F10: Home Office | G10: South | H10: Tennessee | I10: Technology | J10: Phones | K10: Pixel 6 | L10: 4089.31 | M10: 9 | N10: 0.15 | O10: 1726.15 | P10: =O10/L10 -> 0.42211278
A11: ORD-10010 | B11: 44565 | C11: 44571 | D11: C-3646 | E11: Iris Smith | F11: Home Office | G11: Central | H11: Illinois | I11: Technology | J11: Computers | K11: HP Notebook | L11: 8598.87 | M11: 9 | N11: 0 | O11: 3065.68 | P11: =O11/L11 -> 0.35652126
A12: ORD-10011 | B12: 45175 | C12: 45178 | D12: C-8962 | E12: Bob Williams | F12: Consumer | G12: South | H12: Georgia | I12: Furniture | J12: Bookcases | K12: 5-Shelf Bookcase | L12: 115.01 | M12: 1 | N12: 0 | O12: 49.29 | P12: =O12/L12 -> 0.42857143
A13: ORD-10012 | B13: 44693 | C13: 44699 | D13: C-7537 | E13: Frank Davis | F13: Corporate | G13: South | H13: North Carolina | I13: Office Supplies | J13: Appliances | K13: Coffee Maker | L13: 966.49 | M13: 9 | N13: 0.05 | O13: 262.66 | P13: =O13/L13 -> 0.27176691
... A501: ORD-10500 | B501: 45012 | C501: 45016 | D501: C-5036 | E501: Eve Williams | F501: Corporate | G501: Central | H501: Texas | I501: Office Supplies | J501: Storage | K501: Filing Cabinet | L501: 87.33 | M501: 2 | N501: 0.2 | O501: 28.93 | P501: =O501/L501 -> 0.33127219

Sheet Summary_Analysis
A1: 📊 SALES PERFORMANCE SUMMARY DASHBOARD
A3: 📌 KEY METRICS
A4: Total Sales | C4: Total Profit | E4: Avg Margin | G4: Total Orders | I4: Unique Customers
A5: =SUM(Sales_Data!L2:L501) -> 571899.3 | C5: =SUM(Sales_Data!O2:O501) -> 187737.36 | E5: =AVERAGE(Sales_Data!P2:P501) -> 0.32521498 | G5: =COUNTA(Sales_Data!A2:A501) -> 500 | I5: =SUMPRODUCT(1/COUNTIF(Sales_Data!D2:D501,Sales_Data!D2:D501)) -> 494
A8: Sales & Profit by Region | F8: Sales & Profit by Category
A9: Region | B9: Total Sales | C9: Total Profit | D9: Avg Margin | F9: Region | G9: Total Sales | H9: Total Profit | I9: Avg Margin
A10: Central | B10: =SUMIF(Sales_Data!G2:G501,A10,Sales_Data!L2:L501) -> 154825.38 | C10: =SUMIF(Sales_Data!G2:G501,A10,Sales_Data!O2:O501) -> 49271.05 | D10: =AVERAGEIF(Sales_Data!G2:G501,A10,Sales_Data!P2:P501) -> 0.31389617 | F10: Technology | G10: =SUMIF(Sales_Data!I2:I501,F10,Sales_Data!L2:L501) -> 401602.85 | H10: =SUMIF(Sales_Data!I2:I501,F10,Sales_Data!O2:O501) -> 133065.87 | I10: =AVERAGEIF(Sales_Data!I2:I501,F10,Sales_Data!P2:P501) -> 0.32669728
A11: East | B11: =SUMIF(Sales_Data!G2:G501,A11,Sales_Data!L2:L501) -> 129942.57 | C11: =SUMIF(Sales_Data!G2:G501,A11,Sales_Data!O2:O501) -> 41922.27 | D11: =AVERAGEIF(Sales_Data!G2:G501,A11,Sales_Data!P2:P501) -> 0.32689486 | F11: Furniture | G11: =SUMIF(Sales_Data!I2:I501,F11,Sales_Data!L2:L501) -> 127020.61 | H11: =SUMIF(Sales_Data!I2:I501,F11,Sales_Data!O2:O501) -> 40470.84 | I11: =AVERAGEIF(Sales_Data!I2:I501,F11,Sales_Data!P2:P501) -> 0.32170759
A12: South | B12: =SUMIF(Sales_Data!G2:G501,A12,Sales_Data!L2:L501) -> 141611.65 | C12: =SUMIF(Sales_Data!G2:G501,A12,Sales_Data!O2:O501) -> 47214.92 | D12: =AVERAGEIF(Sales_Data!G2:G501,A12,Sales_Data!P2:P501) -> 0.3295989 | F12: Office Supplies | G12: =SUMIF(Sales_Data!I2:I501,F12,Sales_Data!L2:L501) -> 43275.84 | H12: =SUMIF(Sales_Data!I2:I501,F12,Sales_Data!O2:O501) -> 14200.65 | I12: =AVERAGEIF(Sales_Data!I2:I501,F12,Sales_Data!P2:P501) -> 0.32692028
A13: West | B13: =SUMIF(Sales_Data!G2:G501,A13,Sales_Data!L2:L501) -> 145519.7 | C13: =SUMIF(Sales_Data!G2:G501,A13,Sales_Data!O2:O501) -> 49329.12 | D13: =AVERAGEIF(Sales_Data!G2:G501,A13,Sales_Data!P2:P501) -> 0.33255461
A16: Monthly Sales Trend (SUMIFS Formula)
A17: Month | B17: Jan | C17: Feb | D17: Mar | E17: Apr | F17: May | G17: Jun | H17: Jul | I17: Aug | J17: Sep | K17: Oct | L17: Nov | M17: Dec
A18: 2022 | B18: =SUMPRODUCT((YEAR(Sales_Data!B2:B501)=2022)*(MONTH(Sales_Data!B2:B501)=1)*Sales_Data!L2:L501) -> 26133.42 | C18: =SUMPRODUCT((YEAR(Sales_Data!B2:B501)=2022)*(MONTH(Sales_Data!B2:B501)=2)*Sales_Data!L2:L501) -> 36256.65 | D18: =SUMPRODUCT((YEAR(Sales_Data!B2:B501)=2022)*(MONTH(Sales_Data!B2:B501)=3)*Sales_Data!L2:L501) -> 19761.51 | E18: =SUMPRODUCT((YEAR(Sales_Data!B2:B501)=2022)*(MONTH(Sales_Data!B2:B501)=4)*Sales_Data!L2:L501) -> 26016.39 | F18: =SUMPRODUCT((YEAR(Sales_Data!B2:B501)=2022)*(MONTH(Sales_Data!B2:B501)=5)*Sales_Data!L2:L501) -> 9349.3 | G18: =SUMPRODUCT((YEAR(Sales_Data!B2:B501)=2022)*(MONTH(Sales_Data!B2:B501)=6)*Sales_Data!L2:L501) -> 18761.25 | H18: =SUMPRODUCT((YEAR(Sales_Data!B2:B501)=2022)*(MONTH(Sales_Data!B2:B501)=7)*Sales_Data!L2:L501) -> 23501.89 | I18: =SUMPRODUCT((YEAR(Sales_Data!B2:B501)=2022)*(MONTH(Sales_Data!B2:B501)=8)*Sales_Data!L2:L501) -> 25334.49 | J18: =SUMPRODUCT((YEAR(Sales_Data!B2:B501)=2022)*(MONTH(Sales_Data!B2:B501)=9)*Sales_Data!L2:L501) -> 31529.73 | K18: =SUMPRODUCT((YEAR(Sales_Data!B2:B501)=2022)*(MONTH(Sales_Data!B2:B501)=10)*Sales_Data!L2:L501) -> 16955.12 | L18: =SUMPRODUCT((YEAR(Sales_Data!B2:B501)=2022)*(MONTH(Sales_Data!B2:B501)=11)*Sales_Data!L2:L501) -> 7139.16 | M18: =SUMPRODUCT((YEAR(Sales_Data!B2:B501)=2022)*(MONTH(Sales_Data!B2:B501)=12)*Sales_Data!L2:L501) -> 21227.46
A19: 2023 | B19: =SUMPRODUCT((YEAR(Sales_Data!B2:B501)=2023)*(MONTH(Sales_Data!B2:B501)=1)*Sales_Data!L2:L501) -> 23896.35 | C19: =SUMPRODUCT((YEAR(Sales_Data!B2:B501)=2023)*(MONTH(Sales_Data!B2:B501)=2)*Sales_Data!L2:L501) -> 17167.21 | D19: =SUMPRODUCT((YEAR(Sales_Data!B2:B501)=2023)*(MONTH(Sales_Data!B2:B501)=3)*Sales_Data!L2:L501) -> 21521.12 | E19: =SUMPRODUCT((YEAR(Sales_Data!B2:B501)=2023)*(MONTH(Sales_Data!B2:B501)=4)*Sales_Data!L2:L501) -> 26411 | F19: =SUMPRODUCT((YEAR(Sales_Data!B2:B501)=2023)*(MONTH(Sales_Data!B2:B501)=5)*Sales_Data!L2:L501) -> 29873.41 | G19: =SUMPRODUCT((YEAR(Sales_Data!B2:B501)=2023)*(MONTH(Sales_Data!B2:B501)=6)*Sales_Data!L2:L501) -> 22746.86 | H19: =SUMPRODUCT((YEAR(Sales_Data!B2:B501)=2023)*(MONTH(Sales_Data!B2:B501)=7)*Sales_Data!L2:L501) -> 10931.91 | I19: =SUMPRODUCT((YEAR(Sales_Data!B2:B501)=2023)*(MONTH(Sales_Data!B2:B501)=8)*Sales_Data!L2:L501) -> 35982.89 | J19: =SUMPRODUCT((YEAR(Sales_Data!B2:B501)=2023)*(MONTH(Sales_Data!B2:B501)=9)*Sales_Data!L2:L501) -> 36675.76 | K19: =SUMPRODUCT((YEAR(Sales_Data!B2:B501)=2023)*(MONTH(Sales_Data!B2:B501)=10)*Sales_Data!L2:L501) -> 28431.9 | L19: =SUMPRODUCT((YEAR(Sales_Data!B2:B501)=2023)*(MONTH(Sales_Data!B2:B501)=11)*Sales_Data!L2:L501) -> 30354.88 | M19: =SUMPRODUCT((YEAR(Sales_Data!B2:B501)=2023)*(MONTH(Sales_Data!B2:B501)=12)*Sales_Data!L2:L501) -> 25939.64

Sheet 📋 Project Guide
A1: DATA ANALYST PROJECT – INTERMEDIATE LEVEL
A3: STEP 1: EXCEL ANALYSIS
A4: Task | B4: Action
A5: Explore Data | B5: Open Sales_Data sheet → review 500 rows, 16 columns
A6: Pivot Table | B6: Insert > PivotTable → drag Region/Category to Rows, Sales/Profit to Values
A7: Pivot Chart | B7: Select PivotTable → Insert > PivotChart → Clustered Bar
A8: VLOOKUP | B8: Use =VLOOKUP() to enrich data with external lookup tables
A9: Conditional Format | B9: Home > Conditional Formatting > Color Scales on Profit column
A10: Slicers | B10: Insert > Slicer → add Region, Segment, Category for dashboard filtering
A12: STEP 2: SQL ANALYSIS
A13: Task | B13: Query
A14: Import | B14: Load Excel data into SQLite / PostgreSQL / MySQL
A15: Aggregation | B15: SELECT Region, SUM(Sales) FROM orders GROUP BY Region ORDER BY 2 DESC
A16: Window Functions | B16: RANK() OVER (PARTITION BY Category ORDER BY Sales DESC)
A17: CTEs | B17: WITH monthly AS (SELECT ...) SELECT * FROM monthly WHERE ...
A18: Subqueries | B18: Identify customers above average spend with nested SELECT
A20: STEP 3: POWER BI DASHBOARD
A21: Task | B21: Action
A22: Import | B22: Home > Get Data > Excel → connect to this workbook
A23: Relationships | B23: Model View → connect tables on Customer_ID, Product keys
A24: DAX Measures | B24: New Measure: Total Sales = SUM(Sales_Data[Sales])
A25: DAX Measures | B25: Profit Margin = DIVIDE([Total Profit],[Total Sales])
A26: Visuals | B26: Add KPI cards, Bar chart (Region vs Sales), Line (Monthly Trend)
A27: Slicers | B27: Add Year, Region, Segment, Category slicers
A28: Drillthrough | B28: Right-click chart > Add drillthrough page for customer detail
A29: Publish | B29: Publish to Power BI Service → share with stakeholders
